tq_share_sms-1.0.0.dist-info/licenses/LICENSE
tq_sms/__init__.py
tq_sms/client.py
tq_share_sms-1.0.0.dist-info/METADATA
tq_share_sms-1.0.0.dist-info/WHEEL
tq_share_sms-1.0.0.dist-info/top_level.txt
tq_share_sms-1.0.0.dist-info/RECORD
